pathfinding/__init__.py
pathfinding/__main__.py
petchou_pathfinder-0.0.4.dist-info/LICENSE
petchou_pathfinder-0.0.4.dist-info/WHEEL
petchou_pathfinder-0.0.4.dist-info/METADATA
petchou_pathfinder-0.0.4.dist-info/RECORD
