Metadata-Version: 2.1
Name: petchou-pathfinder
Version: 0.0.4
Summary: Path finding library for your projects
Home-page: https://github.com/PetchouDev/PathFinder
Author: PetchouDev
Author-email: petchou91d@gmail.com
Requires-Python: >=3.9,<4.0
Classifier: Programming Language :: Python :: 3
Classifier: Programming Language :: Python :: 3.9
Classifier: Programming Language :: Python :: 3.10
Classifier: Programming Language :: Python :: 3.11
Requires-Dist: termcolor (>=2.1.0,<3.0.0)
Project-URL: Repository, https://github.com/PetchouDev/PathFinder
